[
  {
    "id": "H001",
    "title": "Alen Air Purifier BreatheSmart 75i",
    "category": "Operational Infrastructure",
    "subcategory": "Climate & Wellness",
    "desc": "Commercial-grade HEPA filtration for large office spaces up to 2800 Sq. Ft. Essential for professional air quality.",
    "link": "https://www.amazon.com/dp/B0F99CTJPC",
    "imageUrl": "https://m.media-amazon.com/images/I/71Z8-LpqHGL._AC_SL1500_.jpg"
  },
  {
    "id": "H002",
    "title": "Portable Solar Station 2000W",
    "category": "Energy & Connectivity",
    "subcategory": "Power Resilience",
    "desc": "High-capacity backup power for off-grid project sites and remote business operations.",
    "link": "https://amzn.to/4ukHvbP",
    "imageUrl": "https://m.media-amazon.com/images/I/71Y+O-kZ7DL._AC_SL1500_.jpg"
  },
  {
    "id": "H003",
    "title": "Ergonomic Mesh Task Chair",
    "category": "Operational Infrastructure",
    "subcategory": "Office Furniture",
    "desc": "BIFMA certified executive seating designed for 8+ hours of professional productivity.",
    "link": "#",
    "imageUrl": "https://m.media-amazon.com/images/I/718yTEtHltL._AC_SL1500_.jpg"
  },
  {
    "id": "H004",
    "title": "Starlink Standard Kit",
    "category": "Energy & Connectivity",
    "subcategory": "Global Networking",
    "desc": "High-speed, low-latency satellite internet for remote business connectivity anywhere in the world.",
    "link": "#",
    "imageUrl": "https://m.media-amazon.com/images/I/41-l8vLzZGL._AC_.jpg"
  }
]
